<?xml version="1.0" encoding="UTF-8" standalone="yes"?>

<items>
	<item>
	<title>[COLOR white] [B]Esportes[/B] [/COLOR]</title>
	<link>http://i.imgur.com/KIahmzP.png</link><thumbnail>http://i.imgur.com/KIahmzP.png</thumbnail>
	<externallink>https://raw.githubusercontent.com/Zeke27/list/master/PolaTvSportsChannelList.xml</externallink>
	</item>

	<item>
	<title>[COLOR white] [B]Entretenimento[/B] [/COLOR]</title>
	<link>http://i.imgur.com/KIahmzP.png</link><thumbnail>http://i.imgur.com/KIahmzP.png</thumbnail>
	<externallink>https://raw.githubusercontent.com/Zeke27/list/master/PolaTvEntertainmentChannelList.xml</externallink>
	</item>

	<item>
	<title>[COLOR white] [B]Música[/B] [/COLOR]</title>
	<link>http://i.imgur.com/KIahmzP.png</link><thumbnail>http://i.imgur.com/KIahmzP.png</thumbnail>
	<externallink>https://raw.githubusercontent.com/Zeke27/list/master/PolaTvMusicChannelList.xml</externallink>
	</item>
	
	<item>
	<title>[COLOR white] [B]Filmes e séries[/B] [/COLOR]</title>
	<link>http://i.imgur.com/KIahmzP.png</link><thumbnail>http://i.imgur.com/KIahmzP.png</thumbnail>
	<externallink>https://raw.githubusercontent.com/Zeke27/list/master/PolaTvFSChannelList.xml</externallink>
	</item>

	<item>
	<title>[COLOR white] [B]Internacional[/B] [/COLOR]</title>
	<link>http://i.imgur.com/KIahmzP.png</link><thumbnail>http://i.imgur.com/KIahmzP.png</thumbnail>
	<externallink>http://adrian.kodistream.info/adryan/esp.xml</externallink>
	</item>
</items>



